getpaper/__init__.py
getpaper/cli.py
paper_retriever-0.1.1.dist-info/LICENSE
paper_retriever-0.1.1.dist-info/METADATA
paper_retriever-0.1.1.dist-info/WHEEL
paper_retriever-0.1.1.dist-info/entry_points.txt
paper_retriever-0.1.1.dist-info/RECORD
