Metadata-Version: 2.3
Name: paper-retriever
Version: 0.1.1
Summary: a small command-line tool to get scientific papers from their references
License: GPL-3.0-or-later
Author: Alexandre Dareau
Author-email: alexandre.dareau@protonmail.com
Maintainer: Alexandre Dareau
Maintainer-email: alexandre.dareau@protonmail.com
Requires-Python: >=3.12
Classifier: License :: OSI Approved :: GNU General Public License v3 or later (GPLv3+)
Classifier: Programming Language :: Python :: 3
Classifier: Programming Language :: Python :: 3.12
Classifier: Programming Language :: Python :: 3.13
Requires-Dist: beautifulsoup4 (>=4.13.3,<5.0.0)
Requires-Dist: lxml (>=5.3.1,<6.0.0)
Requires-Dist: requests (>=2.32.3,<3.0.0)
Project-URL: Homepage, https://github.com/adareau/getpaper
Project-URL: Issues, https://github.com/adareau/getpaper/issues
Project-URL: Repository, https://github.com/adareau/getpaper.git
